[{"term_id":55,"name":"\u00e1gil","slug":"agil","taxonomy":"post_tag","description":"","parent":0},{"term_id":56,"name":"agile","slug":"agile","taxonomy":"post_tag","description":"","parent":0},{"term_id":87,"name":"agile sprints","slug":"agile-sprints","taxonomy":"post_tag","description":"","parent":0},{"term_id":82,"name":"agile testing","slug":"agile-testing","taxonomy":"post_tag","description":"","parent":0},{"term_id":39,"name":"AI","slug":"ai","taxonomy":"post_tag","description":"","parent":0},{"term_id":26,"name":"alimentos","slug":"alimentos","taxonomy":"post_tag","description":"","parent":0},{"term_id":62,"name":"amea\u00e7as","slug":"ameacas","taxonomy":"post_tag","description":"","parent":0},{"term_id":45,"name":"an\u00e1lise de dados","slug":"analise-de-dados","taxonomy":"post_tag","description":"","parent":0},{"term_id":63,"name":"aplica\u00e7\u00f5es web","slug":"aplicacoes-web","taxonomy":"post_tag","description":"","parent":0},{"term_id":22,"name":"aplicativos","slug":"aplicativos","taxonomy":"post_tag","description":"","parent":0},{"term_id":77,"name":"arquitetura de software","slug":"arquitetura-de-software","taxonomy":"post_tag","description":"","parent":0},{"term_id":80,"name":"auditoria de c\u00f3digo-fonte","slug":"auditoria-de-codigo-fonte","taxonomy":"post_tag","description":"","parent":0},{"term_id":81,"name":"auditoria de software","slug":"auditoria-de-software","taxonomy":"post_tag","description":"","parent":0},{"term_id":18,"name":"automa\u00e7\u00e3o","slug":"automacao","taxonomy":"post_tag","description":"","parent":0},{"term_id":32,"name":"Automa\u00e7\u00e3o de testes","slug":"automacao-de-testes","taxonomy":"post_tag","description":"","parent":0},{"term_id":27,"name":"big data","slug":"big-data","taxonomy":"post_tag","description":"","parent":0},{"term_id":57,"name":"Business Agility","slug":"business-agility","taxonomy":"post_tag","description":"","parent":0},{"term_id":49,"name":"cdo","slug":"cdo","taxonomy":"post_tag","description":"","parent":0},{"term_id":50,"name":"chief data officer","slug":"chief-data-officer","taxonomy":"post_tag","description":"","parent":0},{"term_id":46,"name":"cientistas de dados","slug":"cientistas-de-dados","taxonomy":"post_tag","description":"","parent":0},{"term_id":47,"name":"compliance","slug":"compliance","taxonomy":"post_tag","description":"","parent":0},{"term_id":83,"name":"Continuous Delivery","slug":"continuous-delivery","taxonomy":"post_tag","description":"","parent":0},{"term_id":84,"name":"Continuous Integration","slug":"continuous-integration","taxonomy":"post_tag","description":"","parent":0},{"term_id":71,"name":"continuous testing","slug":"continuous-testing","taxonomy":"post_tag","description":"","parent":0},{"term_id":72,"name":"cybersecurity","slug":"cybersecurity","taxonomy":"post_tag","description":"","parent":0},{"term_id":33,"name":"dados","slug":"dados","taxonomy":"post_tag","description":"","parent":0},{"term_id":51,"name":"data analytics","slug":"data-analytics","taxonomy":"post_tag","description":"","parent":0},{"term_id":85,"name":"DevOps","slug":"devops","taxonomy":"post_tag","description":"","parent":0},{"term_id":86,"name":"devsecops","slug":"devsecops","taxonomy":"post_tag","description":"","parent":0},{"term_id":19,"name":"digital workplace","slug":"digital-workplace","taxonomy":"post_tag","description":"","parent":0},{"term_id":43,"name":"experi\u00eancia do consumidor","slug":"experiencia-do-consumidor","taxonomy":"post_tag","description":"","parent":0},{"term_id":60,"name":"gerenciamento de dados","slug":"gerenciamento-de-dados","taxonomy":"post_tag","description":"","parent":0},{"term_id":58,"name":"gest\u00e3o de vulnerabilidades","slug":"gestao-de-vulnerabilidades","taxonomy":"post_tag","description":"","parent":0},{"term_id":61,"name":"governan\u00e7a","slug":"governanca","taxonomy":"post_tag","description":"","parent":0},{"term_id":28,"name":"inteligencia artificial","slug":"inteligencia-artificial","taxonomy":"post_tag","description":"","parent":0},{"term_id":29,"name":"internet das coisas","slug":"internet-das-coisas","taxonomy":"post_tag","description":"","parent":0},{"term_id":78,"name":"layered pattern","slug":"layered-pattern","taxonomy":"post_tag","description":"","parent":0},{"term_id":24,"name":"lean","slug":"lean","taxonomy":"post_tag","description":"","parent":0},{"term_id":79,"name":"microsservices pattern","slug":"microsservices-pattern","taxonomy":"post_tag","description":"","parent":0},{"term_id":52,"name":"midia paga","slug":"midia-paga","taxonomy":"post_tag","description":"","parent":0},{"term_id":74,"name":"nuvem nativa","slug":"nuvem-nativa","taxonomy":"post_tag","description":"","parent":0},{"term_id":53,"name":"otimiza\u00e7\u00e3o de sites","slug":"otimizacao-de-sites","taxonomy":"post_tag","description":"","parent":0},{"term_id":25,"name":"prime talk","slug":"prime-talk","taxonomy":"post_tag","description":"","parent":0},{"term_id":35,"name":"Produtos Sap","slug":"produtos-sap","taxonomy":"post_tag","description":"","parent":0},{"term_id":21,"name":"projetos","slug":"projetos","taxonomy":"post_tag","description":"","parent":0},{"term_id":66,"name":"QA","slug":"qa","taxonomy":"post_tag","description":"","parent":0},{"term_id":67,"name":"qualidade de software","slug":"qualidade-de-software","taxonomy":"post_tag","description":"","parent":0},{"term_id":68,"name":"quality assurance","slug":"quality-assurance","taxonomy":"post_tag","description":"","parent":0},{"term_id":73,"name":"ransomwares","slug":"ransomwares","taxonomy":"post_tag","description":"","parent":0},{"term_id":40,"name":"rob\u00f4s","slug":"robos","taxonomy":"post_tag","description":"","parent":0},{"term_id":41,"name":"RPA","slug":"rpa","taxonomy":"post_tag","description":"","parent":0},{"term_id":34,"name":"SAP","slug":"sap","taxonomy":"post_tag","description":"","parent":0},{"term_id":23,"name":"seguran\u00e7a","slug":"seguranca","taxonomy":"post_tag","description":"","parent":0},{"term_id":64,"name":"seguran\u00e7a de aplica\u00e7\u00f5es","slug":"seguranca-de-aplicacoes","taxonomy":"post_tag","description":"","parent":0},{"term_id":54,"name":"SEO","slug":"seo","taxonomy":"post_tag","description":"","parent":0},{"term_id":30,"name":"setor alimenticio","slug":"setor-alimenticio","taxonomy":"post_tag","description":"","parent":0},{"term_id":69,"name":"software quality assurance","slug":"software-quality-assurance","taxonomy":"post_tag","description":"","parent":0},{"term_id":36,"name":"solution manager","slug":"solution-manager","taxonomy":"post_tag","description":"","parent":0},{"term_id":70,"name":"SQA","slug":"sqa","taxonomy":"post_tag","description":"","parent":0},{"term_id":44,"name":"TDWC","slug":"tdwc","taxonomy":"post_tag","description":"","parent":0},{"term_id":42,"name":"tecnologia digital","slug":"tecnologia-digital","taxonomy":"post_tag","description":"","parent":0},{"term_id":37,"name":"test suite","slug":"test-suite","taxonomy":"post_tag","description":"","parent":0},{"term_id":38,"name":"Testes","slug":"testes","taxonomy":"post_tag","description":"","parent":0},{"term_id":65,"name":"testes automatizados","slug":"testes-automatizados","taxonomy":"post_tag","description":"","parent":0},{"term_id":75,"name":"testes de software","slug":"testes-de-software","taxonomy":"post_tag","description":"","parent":0},{"term_id":76,"name":"testes de software em nuvem","slug":"testes-de-software-em-nuvem","taxonomy":"post_tag","description":"","parent":0},{"term_id":48,"name":"testing","slug":"testing","taxonomy":"post_tag","description":"","parent":0},{"term_id":89,"name":"Trabalho H\u00edbrido","slug":"trabalho-hibrido","taxonomy":"post_tag","description":"","parent":0},{"term_id":90,"name":"Trabalho Remoto","slug":"trabalho-remoto","taxonomy":"post_tag","description":"","parent":0},{"term_id":88,"name":"transforma\u00e7\u00e3o \u00e1gil","slug":"transformacao-agil","taxonomy":"post_tag","description":"","parent":0},{"term_id":31,"name":"transformacao digital","slug":"transformacao-digital","taxonomy":"post_tag","description":"","parent":0},{"term_id":59,"name":"vulnerabilidades","slug":"vulnerabilidades","taxonomy":"post_tag","description":"","parent":0}]